MANIFEST.in
setup.py
basemap/__init__.py
basemap/abc.py
basemap/basemap.py
basemap/bostonharbor_coast.dat
basemap/capecod_outline.dat
basemap/cascobay_coast.dat
basemap/necoast_noaa.dat
basemap/necscoast_noaa.dat
basemap/necscoast_worldvec.dat
basemap/penbay_coast.dat
basemap/sne_coast.dat
basemap_Jim.egg-info/PKG-INFO
basemap_Jim.egg-info/SOURCES.txt
basemap_Jim.egg-info/dependency_links.txt
basemap_Jim.egg-info/requires.txt
basemap_Jim.egg-info/top_level.txt