Metadata-Version: 1.1
Name: basemap-Jim
Version: 0.1.1
Summary: basemap of Northwestern Atlantic Coastline for python plotting  .
Home-page: https://github.com/xhx509/drifter
Author: Jammes Manning
Author-email: james.manning@noaa.gov
License: update soon
Keywords: basemap,python,python plot
Platform: UNKNOWN
Classifier: Programming Language :: Python
Classifier: Environment :: Other Environment
